pathology/__init__.py
pathology/path.py
pathology-0.2.dist-info/LICENSE
pathology-0.2.dist-info/METADATA
pathology-0.2.dist-info/WHEEL
pathology-0.2.dist-info/top_level.txt
pathology-0.2.dist-info/RECORD
