Metadata-Version: 2.1
Name: pathology
Version: 0.2
Summary: Add static script_dir() method to pathlib.Path
Home-page: https://github.com/the-gigi/pathology
Author: Gigi Sayfan
Author-email: the.gigi@gmail.com
License: MIT
Platform: UNKNOWN
